abacus/__init__.py
abacus/base.py
abacus/book.py
abacus/chart.py
abacus/entry.py
abacus/ledger.py
abacus_minimal-0.14.2.dist-info/METADATA
abacus_minimal-0.14.2.dist-info/WHEEL
abacus_minimal-0.14.2.dist-info/RECORD
