Metadata-Version: 2.1
Name: abacus-minimal
Version: 0.14.2
Summary: Ledger in Python that follows corporate accounting rules.
License: MIT
Author: Evgeny Pogrebnyak
Author-email: e.pogrebnyak@gmail.com
Requires-Python: >=3.10,<4.0
Classifier: License :: OSI Approved :: MIT License
Classifier: Programming Language :: Python :: 3
Classifier: Programming Language :: Python :: 3.10
Classifier: Programming Language :: Python :: 3.11
Classifier: Programming Language :: Python :: 3.12
Requires-Dist: pydantic (>=2.9.2,<3.0.0)
Requires-Dist: simplejson (>=3.19.3,<4.0.0)
